{
  "name": "eoffice-portal",
  "version": "1.0.0",
  "description": "eOffice - Cổng Thông Tin Nội Bộ Doanh Nghiệp. Hệ thống truyền thông nội bộ, quản lý văn bản và phê duyệt quy trình.",
  "buildDate": "2026-07-04T13:29:43.070Z",
  "buildTimestamp": 1783171783070,
  "files": {
    "index.html": {
      "original": 100556,
      "minified": 73283
    },
    "css/styles.css": {
      "original": 67887,
      "minified": 52889
    },
    "js/app.js": {
      "original": 188872,
      "minified": 188872
    }
  }
}